memor/__init__.py
memor/errors.py
memor/functions.py
memor/keywords.py
memor/message.py
memor/params.py
memor/prompt.py
memor/response.py
memor/session.py
memor/template.py
memor/tokens_estimator.py
memor-1.0.dist-info/licenses/AUTHORS.md
memor-1.0.dist-info/licenses/LICENSE
memor-1.0.dist-info/METADATA
memor-1.0.dist-info/WHEEL
memor-1.0.dist-info/top_level.txt
memor-1.0.dist-info/RECORD
